qixinApi/__init__.py
qixinApi/qixinApi.py
qixinApi-0.0.7.dist-info/METADATA
qixinApi-0.0.7.dist-info/WHEEL
qixinApi-0.0.7.dist-info/top_level.txt
qixinApi-0.0.7.dist-info/RECORD
