Metadata-Version: 2.1
Name: qixinApi
Version: 0.0.7
Summary: 齐欣云服接口
Home-page: https://github.com/seoktaehyeon/qixin-api
Author: Will
Author-email: v.stone@163.com
Maintainer: Will
Maintainer-email: v.stone@163.com
License: MIT
Platform: any
Requires-Dist: requests
